scss/__init__.py
scss/__main__.py
scss/ast.py
scss/calculator.py
scss/compiler.py
scss/config.py
scss/cssdefs.py
scss/errors.py
scss/legacy.py
scss/less2scss.py
scss/namespace.py
scss/rule.py
scss/scss_meta.py
scss/selector.py
scss/setup.py
scss/source.py
scss/tool.py
scss/types.py
scss/util.py
scss/src/block_locator.h
scss/src/hashtable.h
scss/src/py3defs.h
scss/src/scanner.h
scss/src/utils.h
cpfr_pyScss-1.4.1.dist-info/LICENSE
cpfr_pyScss-1.4.1.dist-info/METADATA
cpfr_pyScss-1.4.1.dist-info/WHEEL
cpfr_pyScss-1.4.1.dist-info/top_level.txt
cpfr_pyScss-1.4.1.dist-info/RECORD
