Metadata-Version: 2.2
Name: cpfr-pyScss
Version: 1.4.1
Summary: fork of pyScss - pyScss is a compiler for the Sass language, a superset of CSS3 that adds programming capabilities and some other syntactic sugar.
Home-page: http://github.com/Kronuz/pyScss
Download-URL: http://github.com/Kronuz/pyScss/tarball/v1.4.0
Author: German M. Bravo (Kronuz)
Author-email: Carsten Pfeffer <pfeffer.carsten@gmail.com>
License: MIT
Keywords: css,oocss,xcss,sass,scss,less,precompiler
Classifier: Development Status :: 5 - Production/Stable
Classifier: Intended Audience :: Developers
Classifier: License :: OSI Approved :: MIT License
Classifier: Operating System :: OS Independent
Classifier: Programming Language :: Python
Classifier: Programming Language :: Python :: 3
Classifier: Topic :: Software Development :: Code Generators
Classifier: Topic :: Text Processing :: Markup
Classifier: Topic :: Software Development :: Libraries :: Python Modules
Requires-Python: >=3.11
License-File: LICENSE
Dynamic: author
Dynamic: classifier
Dynamic: download-url
Dynamic: home-page
Dynamic: license
